README.md
setup.py
android_stt/__init__.py
android_stt/version.py
android_stt.egg-info/PKG-INFO
android_stt.egg-info/SOURCES.txt
android_stt.egg-info/dependency_links.txt
android_stt.egg-info/top_level.txt